scrapy_puppeteer/__init__.py
scrapy_puppeteer/cli.py
scrapy_puppeteer/http.py
scrapy_puppeteer/middlewares.py
scrapy_puppeteer-0.0.1b0.dist-info/METADATA
scrapy_puppeteer-0.0.1b0.dist-info/RECORD
scrapy_puppeteer-0.0.1b0.dist-info/WHEEL
scrapy_puppeteer-0.0.1b0.dist-info/entry_points.txt
scrapy_puppeteer-0.0.1b0.dist-info/top_level.txt
tests/__init__.py
tests/test_middlewares.py
