Metadata-Version: 2.1
Name: scrapy-puppeteer
Version: 0.0.1b0
Summary: Scrapy with puppeteer
Home-page: https://github.com/clemfromspace/scrapy-puppeteer
Author: UNKNOWN
Author-email: UNKNOWN
License: UNKNOWN
Platform: UNKNOWN
Requires-Dist: scrapy (>=1.0.0)
Requires-Dist: pyppeteer
